{
  "project_info": {
    "project_number": "865805464805",
    "firebase_url": "https://complainreportingapp.firebaseio.com",
    "project_id": "complainreportingapp",
    "storage_bucket": "complainreportingapp.appspot.com"
  },
  "client": [
    {
      "client_info": {
        "mobilesdk_app_id": "1:865805464805:android:8fcbe6281a7296336c900c",
        "android_client_info": {
          "package_name": "com.array.complainreportingapp"
        }
      },
      "oauth_client": [
        {
          "client_id": "865805464805-v1c1tsncnlg2rsceag144f98rhc69dnn.apps.googleusercontent.com",
          "client_type": 3
        }
      ],
      "api_key": [
        {
          "current_key": "AIzaSyB3_zcHx0qhlsZ07MI0mbsMLcHwMlR_RXg"
        }
      ],
      "services": {
        "appinvite_service": {
          "other_platform_oauth_client": [
            {
              "client_id": "865805464805-v1c1tsncnlg2rsceag144f98rhc69dnn.apps.googleusercontent.com",
              "client_type": 3
            }
          ]
        }
      }
    }
  ],
  "configuration_version": "1"
}